README.md
setup.py
getchwrap/__init__.py
getchwrap/_version.py
getchwrap/getchwrap.py
getchwrap.egg-info/PKG-INFO
getchwrap.egg-info/SOURCES.txt
getchwrap.egg-info/dependency_links.txt
getchwrap.egg-info/entry_points.txt
getchwrap.egg-info/requires.txt
getchwrap.egg-info/top_level.txt