Metadata-Version: 1.0
Name: getchwrap
Version: 20201123.0
Summary: A subprocess wrapper to ergonomically enhance tty user input
Home-page: https://github.com/erjoalgo/getchwrap
Author: Ernesto Alfonso
Author-email: erjoalgo@gmail.com
License: GPLv3
Platform: UNKNOWN
